kompy/__init__.py
kompy/authentication.py
kompy/coordinate.py
kompy/difficulty.py
kompy/image.py
kompy/komoot_connector.py
kompy/segment.py
kompy/surface.py
kompy/tour.py
kompy/way_type.py
kompy/constants/__init__.py
kompy/constants/activities.py
kompy/constants/difficulty_grade.py
kompy/constants/privacy_status.py
kompy/constants/query_parameters.py
kompy/constants/segment_type.py
kompy/constants/surface.py
kompy/constants/tour_constants.py
kompy/constants/tour_object_types.py
kompy/constants/urls.py
kompy/constants/way_type.py
kompy/constants/waypoint.py
kompy/errors/__init__.py
kompy/errors/initialisation_errors.py
kompy/errors/privacy_errors.py
kompy-0.0.12.dist-info/METADATA
kompy-0.0.12.dist-info/WHEEL
kompy-0.0.12.dist-info/top_level.txt
kompy-0.0.12.dist-info/RECORD
