Metadata-Version: 2.4
Name: Kompy
Version: 0.0.12
Summary: A Python wrapper for Komoot APIs
Author-email: Matteo Villosio <github@matteovillosio.com>
Project-URL: Homepage, https://github.com/tsadoq/kompy
Project-URL: Bug Tracker, https://github.com/tsadoq/kompy/issues
Classifier: Programming Language :: Python :: 3
Classifier: Operating System :: OS Independent
Requires-Python: >=3.11
Requires-Dist: dateutils>=0.6.12
Requires-Dist: python-dateutil>=2.8.2
Requires-Dist: requests>=2.31.0
Requires-Dist: pillow>=10.1.0
Requires-Dist: gpxpy>=1.6.1
Requires-Dist: fit_tool>=0.9.13
Requires-Dist: pdoc>=14.1.0
